elevaso_spine/__init__.py
elevaso_spine/app/caller.py
elevaso_spine/calc/hsh.py
elevaso_spine/cli/args.py
elevaso_spine/cli/exc.py
elevaso_spine/cli/setup.py
elevaso_spine/cli/ver.py
elevaso_spine/dtm/now.py
elevaso_spine/environ/load.py
elevaso_spine/environ/var.py
elevaso_spine/fmt/sub.py
elevaso_spine/fobj/find_obj.py
elevaso_spine/itr/itr.py
elevaso_spine/log/append.py
elevaso_spine/log/config.py
elevaso_spine/log/fmt.py
elevaso_spine/log/fmt_json.py
elevaso_spine/log/fmt_standard.py
elevaso_spine/log/data/default_logging_json.json
elevaso_spine/log/data/default_logging_standard.json
elevaso_spine/rule/base.py
elevaso_spine/rule/engine.py
elevaso_spine/rule/eval.py
elevaso_spine/rule/explain.py
elevaso_spine/rule/operators.py
elevaso_spine/rule/validate.py
elevaso_spine/thrd/base.py
elevaso_spine/thrd/mgr.py
elevaso_spine-0.2.0.dist-info/licenses/LICENSE
elevaso_spine-0.2.0.dist-info/METADATA
elevaso_spine-0.2.0.dist-info/WHEEL
elevaso_spine-0.2.0.dist-info/top_level.txt
elevaso_spine-0.2.0.dist-info/RECORD
